{
  "message_name": "UBX-RXM-RAWX",
  "num_extractions": 14,
  "adjudication": {
    "canonical_structure": {
      "ubx_message": {
        "class_id": "0x02",
        "message_id": "0x15",
        "name": "UBX-RXM-RAWX",
        "description": "Multi-GNSS raw measurements",
        "payload_length": {
          "variable": {
            "base": 16,
            "formula": "16 + numMeas * 32"
          }
        },
        "fields": [
          {
            "byte_offset": 0,
            "data_type": "R8",
            "name": "rcvTow",
            "unit": "s",
            "description": "Measurement time of week in receiver local time approximately aligned to the GPS time system."
          },
          {
            "byte_offset": 8,
            "data_type": "U2",
            "name": "week",
            "unit": "weeks",
            "description": "GPS week number in receiver local time."
          },
          {
            "byte_offset": 10,
            "data_type": "I1",
            "name": "leaps",
            "unit": "s",
            "description": "GPS leap seconds (GPS-UTC)."
          },
          {
            "byte_offset": 11,
            "data_type": "U1",
            "name": "numMeas",
            "description": "Number of measurements to follow"
          },
          {
            "byte_offset": 12,
            "data_type": "X1",
            "name": "recStat",
            "description": "Receiver tracking status bitfield",
            "bit_fields": [
              {
                "bit_offset": 0,
                "name": "leapSec",
                "description": "Leap seconds have been determined"
              },
              {
                "bit_offset": 1,
                "name": "clkReset",
                "description": "Clock reset applied"
              }
            ]
          },
          {
            "byte_offset": 13,
            "data_type": "U1",
            "name": "version",
            "description": "Message version (0x01 for this version)"
          },
          {
            "byte_offset": 14,
            "data_type": {
              "array_of": "U1",
              "count": 2
            },
            "name": "reserved0",
            "reserved": true
          }
        ],
        "repeated_group": {
          "num_repeats_field_name": "numMeas",
          "group_size": 32,
          "fields": [
            {
              "byte_offset": 0,
              "data_type": "R8",
              "name": "prMes",
              "unit": "m",
              "description": "Pseudorange measurement"
            },
            {
              "byte_offset": 8,
              "data_type": "R8",
              "name": "cpMes",
              "unit": "cycles",
              "description": "Carrier phase measurement"
            },
            {
              "byte_offset": 16,
              "data_type": "R4",
              "name": "doMes",
              "unit": "Hz",
              "description": "Doppler measurement"
            },
            {
              "byte_offset": 20,
              "data_type": "U1",
              "name": "gnssId",
              "description": "GNSS identifier"
            },
            {
              "byte_offset": 21,
              "data_type": "U1",
              "name": "svId",
              "description": "Satellite identifier"
            },
            {
              "byte_offset": 22,
              "data_type": "U1",
              "name": "sigId",
              "description": "New style signal identifier"
            },
            {
              "byte_offset": 23,
              "data_type": "U1",
              "name": "freqId",
              "description": "GLONASS frequency slot + 7"
            },
            {
              "byte_offset": 24,
              "data_type": "U2",
              "name": "locktime",
              "unit": "ms",
              "description": "Carrier phase locktime counter"
            },
            {
              "byte_offset": 26,
              "data_type": "U1",
              "name": "cno",
              "unit": "dBHz",
              "description": "Carrier-to-noise density ratio"
            },
            {
              "byte_offset": 27,
              "data_type": "X1",
              "name": "prStdev",
              "unit": "m",
              "description": "Estimated pseudorange measurement standard deviation",
              "formula": "0.01 * 2^prStd"
            },
            {
              "byte_offset": 28,
              "data_type": "X1",
              "name": "cpStdev",
              "unit": "cycles",
              "description": "Estimated carrier phase measurement standard deviation",
              "formula": "0.004"
            },
            {
              "byte_offset": 29,
              "data_type": "X1",
              "name": "doStdev",
              "unit": "Hz",
              "description": "Estimated Doppler measurement standard deviation",
              "formula": "0.002 * 2^doStd"
            },
            {
              "byte_offset": 30,
              "data_type": "X1",
              "name": "trkStat",
              "description": "Tracking status bitfield",
              "bit_fields": [
                {
                  "bit_offset": 0,
                  "name": "prValid"
                },
                {
                  "bit_offset": 1,
                  "name": "cpValid"
                },
                {
                  "bit_offset": 2,
                  "name": "halfCyc"
                },
                {
                  "bit_offset": 3,
                  "name": "subHalfCyc"
                }
              ]
            },
            {
              "byte_offset": 31,
              "data_type": "U1",
              "name": "reserved1",
              "reserved": true
            }
          ]
        }
      }
    },
    "canonical_confidence": "high",
    "extraction_verdicts": [
      {
        "source": "u-blox-F9-TIM-2.20_InterfaceDescription_UBX-21048598",
        "verdict": "correct",
        "issues": []
      },
      {
        "source": "F9-HPS120_Interfacedescription_UBX-19056845",
        "verdict": "correct",
        "issues": []
      },
      {
        "source": "u-blox-X20-HPG-2.02_InterfaceDescription_UBXDOC-304424225-19967",
        "verdict": "correct",
        "issues": []
      },
      {
        "source": "u-blox-M10-SPG-5.30_InterfaceDescription_UBXDOC-304424225-20395",
        "verdict": "valid_variation",
        "issues": [
          "Uses 'leapS' terminology instead of 'leaps'",
          "Explicitly defines cpStdev scaling as 0.004 * 2^n"
        ]
      },
      {
        "source": "u-blox-F9-HPS-1.30_InterfaceDescription_UBX-22010984",
        "verdict": "correct",
        "issues": []
      },
      {
        "source": "u-blox-F9-TIM-2.25_InterfaceDescription_UBXDOC-963802114-13231",
        "verdict": "correct",
        "issues": []
      },
      {
        "source": "u-blox-F9-LAP-1.30_InterfaceDescription_UBX-22005157",
        "verdict": "correct",
        "issues": []
      },
      {
        "source": "u-blox-F9-DBD-1.30_InterfaceDescription_UBX-23006360",
        "verdict": "correct",
        "issues": []
      },
      {
        "source": "u-blox-F9-HPG-1.13_InterfaceDescription_UBX-21023318",
        "verdict": "correct",
        "issues": []
      },
      {
        "source": "u-blox-F9-LAP-1.50_InterfaceDescription_UBXDOC-963802114-13052",
        "verdict": "correct",
        "issues": []
      },
      {
        "source": "u-blox8-M8_ReceiverDescrProtSpec_UBX-13003221",
        "verdict": "valid_variation",
        "issues": [
          "Uses 'reserved1' for header and 'reserved2' for group reserved fields"
        ]
      },
      {
        "source": "u-blox-F9-HPG-1.32_InterfaceDescription_UBX-22008968",
        "verdict": "correct",
        "issues": []
      },
      {
        "source": "M9-ADR-5.10_InterfaceDescription_UBX-20048972_C1-Public",
        "verdict": "extraction_error",
        "issues": [
          "Repeated group field offsets are absolute (starting at 16) rather than relative to group start (starting at 0)"
        ]
      },
      {
        "source": "u-blox-F9-HPG-L1L5-1.40_InterfaceDescription_UBX-23006991",
        "verdict": "correct",
        "issues": []
      }
    ],
    "valid_variations": [
      {
        "sources": [
          "u-blox-M10-SPG-5.30_InterfaceDescription_UBXDOC-304424225-20395"
        ],
        "structure": {
          "field_leaps_name": "leapS",
          "cpStdev_scaling": "0.004 * 2^n"
        },
        "reason": "M10 generation documentation uses slightly different field naming conventions and provides more detail on the exponential scaling of standard deviation fields."
      },
      {
        "sources": [
          "u-blox8-M8_ReceiverDescrProtSpec_UBX-13003221"
        ],
        "structure": {
          "reserved_field_names": [
            "reserved1",
            "reserved2"
          ]
        },
        "reason": "Older generation (u-blox 8) manuals often iterate reserved field names globally across the message rather than resetting per group."
      }
    ],
    "reasoning": "The UBX-RXM-RAWX message is highly consistent across u-blox 8, 9, and 10 generations. It consists of a 16-byte fixed header containing timing and status information, followed by N 32-byte measurement blocks. Extraction 13 failed because it provided absolute offsets for the repeated fields instead of group-relative offsets. Extraction 4 (M10) and Extraction 11 (u-blox 8) are correct representations of their specific generation's documentation style variations."
  }
}